CHANGELOG.md
MANIFEST.in
README.md
main-cli.py
project.json
setup.py
crawl_me/__init__.py
crawl_me/__projconf__.py
crawl_me/sysconf.py
crawl_me.egg-info/PKG-INFO
crawl_me.egg-info/SOURCES.txt
crawl_me.egg-info/dependency_links.txt
crawl_me.egg-info/entry_points.txt
crawl_me.egg-info/requires.txt
crawl_me.egg-info/top_level.txt
crawl_me/common/__init__.py
crawl_me/common/__main__.py
crawl_me/common/crawlercore.py
crawl_me/common/rangedownloader.py
crawl_me/common/utils.py
crawl_me/plugin/__init__.py
crawl_me/plugin/baseHandler.py
crawl_me/plugin/gamersky.py
crawl_me/plugin/pageBasedHandler.py
crawl_me/plugin/pixiv.py
crawl_me/third_party/__init__.py
crawl_me/third_party/abc.py