Metadata-Version: 1.1
Name: crawl-me
Version: 0.1.9dev-20140619-2
Summary: This is a plugin based web picture crawler. Now pixiv/gamersky plugin available!
Home-page: https://github.com/nyankosama/crawl-me
Author: Liangrui He
Author-email: i@nyankosama.com
License: MIT
Keywords: c,r,a,w,l,e,r, ,d,o,w,n,l,o,a,d,e,r, ,p,i,c,t,u,r,e, ,p,i,x,i,v
Platform: any
Classifier: Development Status :: 2 - Pre-Alpha
Classifier: Environment :: Console
Classifier: Environment :: Web Environment
Classifier: Intended Audience :: End Users/Desktop
Classifier: Intended Audience :: Developers
Classifier: License :: OSI Approved :: MIT License
Classifier: Natural Language :: English
Classifier: Operating System :: OS Independent
Classifier: Programming Language :: Python :: 2.7
Classifier: Topic :: Internet
Classifier: Topic :: Internet :: WWW/HTTP
Classifier: Topic :: System :: Networking
Classifier: Topic :: Utilities
